{"columns": ["Name", "Average Price", "Total Market", "Total Quantity", "id"], "items": [{"Name": "Timeworn Leather Map", "Average Price": 28229, "Total Market": 366988, "Total Quantity": 13, "id": 6688}, {"Name": "Timeworn Goatskin Map", "Average Price": 5772, "Total Market": 155869, "Total Quantity": 27, "id": 6689}, {"Name": "Timeworn Toadskin Map", "Average Price": 13518, "Total Market": 324446, "Total Quantity": 24, "id": 6690}, {"Name": "Timeworn Boarskin Map", "Average Price": 34488, "Total Market": 482842, "Total Quantity": 14, "id": 6691}, {"Name": "Timeworn Peisteskin Map", "Average Price": 37827, "Total Market": 832194, "Total Quantity": 22, "id": 6692}, {"Name": "Timeworn Archaeoskin Map", "Average Price": 8252, "Total Market": 519925, "Total Quantity": 63, "id": 12241}, {"Name": "Timeworn Wyvernskin Map", "Average Price": 24787, "Total Market": 1165035, "Total Quantity": 47, "id": 12242}, {"Name": "Timeworn Dragonskin Map", "Average Price": 41863, "Total Market": 2386211, "Total Quantity": 57, "id": 12243}, {"Name": "Timeworn Gaganaskin Map", "Average Price": 21411, "Total Market": 727978, "Total Quantity": 34, "id": 17835}, {"Name": "Timeworn Gazelleskin Map", "Average Price": 30450, "Total Market": 3440926, "Total Quantity": 113, "id": 17836}, {"Name": "Timeworn Gliderskin Map", "Average Price": 16073, "Total Market": 916180, "Total Quantity": 57, "id": 26744}, {"Name": "Timeworn Zonureskin Map", "Average Price": 37140, "Total Market": 5756701, "Total Quantity": 155, "id": 26745}, {"Name": "Timeworn Saigaskin Map", "Average Price": 9629, "Total Market": 414055, "Total Quantity": 43, "id": 36611}, {"Name": "Timeworn Kumbhiraskin Map", "Average Price": 17940, "Total Market": 3229327, "Total Quantity": 180, "id": 36612}, {"Name": "Timeworn Ophiotauroskin Map", "Average Price": 16212, "Total Market": 6744240, "Total Quantity": 416, "id": 39591}]}