{"columns": ["Name", "Average Price", "Total Market", "Total Quantity", "cost", "id", "lodestone_id", "Price/Cost"], "items": [{"Name": "Gatherer's Guerdon Materia X", "Average Price": 7445, "Total Market": 5569305, "Total Quantity": 748, "cost": 500, "id": 33935, "lodestone_id": "e1fb2fce8e4", "Price/Cost": 14.89}, {"Name": "Gatherer's Guile Materia X", "Average Price": 4574, "Total Market": 10627676, "Total Quantity": 2323, "cost": 500, "id": 33936, "lodestone_id": "2ca53d27bc7", "Price/Cost": 9.148}, {"Name": "Gatherer's Grasp Materia X", "Average Price": 3150, "Total Market": 2801073, "Total Quantity": 889, "cost": 500, "id": 33937, "lodestone_id": "dbcdf2f7e5a", "Price/Cost": 6.3}, {"Name": "Moonlight Aethersand", "Average Price": 457, "Total Market": 1244630, "Total Quantity": 2722, "cost": 100, "id": 36223, "lodestone_id": "530b41e6904", "Price/Cost": 4.57}, {"Name": "Endstone Aethersand", "Average Price": 79, "Total Market": 7821, "Total Quantity": 99, "cost": 200, "id": 36224, "lodestone_id": "7cf1c093d2f", "Price/Cost": 0.395}, {"Name": "Endwood Aethersand", "Average Price": 89, "Total Market": 14523, "Total Quantity": 163, "cost": 200, "id": 36225, "lodestone_id": "780155566da", "Price/Cost": 0.445}, {"Name": "Endtide Aethersand", "Average Price": 96, "Total Market": 2319, "Total Quantity": 24, "cost": 200, "id": 36226, "lodestone_id": "b62cae80c45", "Price/Cost": 0.48}, {"Name": "Earthbreak Aethersand", "Average Price": 1632, "Total Market": 12500286, "Total Quantity": 7655, "cost": 300, "id": 38936, "lodestone_id": "f1b47a16a63", "Price/Cost": 5.44}, {"Name": "Mackerel Strip", "Average Price": 581, "Total Market": 1256532, "Total Quantity": 2162, "cost": 5, "id": 36593, "lodestone_id": "0ef0fee1c1e", "Price/Cost": 116.2}, {"Name": "Mayfly", "Average Price": 517, "Total Market": 520208, "Total Quantity": 1005, "cost": 5, "id": 36591, "lodestone_id": "e2052da1632", "Price/Cost": 103.4}, {"Name": "Stardust", "Average Price": 364, "Total Market": 78058, "Total Quantity": 214, "cost": 5, "id": 36597, "lodestone_id": "c5470744990", "Price/Cost": 72.8}]}