{"columns": ["Name", "Average Price", "Total Market", "Total Quantity", "cost", "id", "Price/Cost"], "items": [{"Name": "Albino Karakul Horn", "Average Price": 853399, "Total Market": 4266999, "Total Quantity": 5, "cost": 8400, "id": 28125, "Price/Cost": 101.59511904761905}, {"Name": "Ballroom Etiquette - Uncouth Congratulations", "Average Price": 318407, "Total Market": 3820894, "Total Quantity": 12, "cost": 1800, "id": 31401, "Price/Cost": 176.89277777777778}, {"Name": "Ruby Red Dye", "Average Price": 10044, "Total Market": 4961952, "Total Quantity": 494, "cost": 100, "id": 30116, "Price/Cost": 100.44}, {"Name": "Cherry Pink Dye", "Average Price": 9628, "Total Market": 2628571, "Total Quantity": 273, "cost": 100, "id": 30117, "Price/Cost": 96.28}, {"Name": "Canary Yellow Dye", "Average Price": 10327, "Total Market": 351145, "Total Quantity": 34, "cost": 100, "id": 30118, "Price/Cost": 103.27}, {"Name": "Vanilla Yellow Dye", "Average Price": 5241, "Total Market": 592302, "Total Quantity": 113, "cost": 100, "id": 30119, "Price/Cost": 52.41}, {"Name": "Dragoon Blue Dye", "Average Price": 9535, "Total Market": 1907175, "Total Quantity": 200, "cost": 100, "id": 30120, "Price/Cost": 95.35}, {"Name": "Turquoise Blue Dye", "Average Price": 10172, "Total Market": 946067, "Total Quantity": 93, "cost": 100, "id": 30121, "Price/Cost": 101.72}, {"Name": "Gunmetal Black Dye", "Average Price": 24046, "Total Market": 8464383, "Total Quantity": 352, "cost": 500, "id": 30122, "Price/Cost": 48.092}, {"Name": "Pearl White Dye", "Average Price": 23772, "Total Market": 7583522, "Total Quantity": 319, "cost": 500, "id": 30123, "Price/Cost": 47.544}, {"Name": "Metallic Brass Dye", "Average Price": 26871, "Total Market": 2149724, "Total Quantity": 80, "cost": 500, "id": 30124, "Price/Cost": 53.742}, {"Name": "Ballroom Etiquette - Concealing Meals", "Average Price": 293656, "Total Market": 2349254, "Total Quantity": 8, "cost": 1800, "id": 32826, "Price/Cost": 163.14222222222222}, {"Name": "Oddly Specific Cedar Log", "Average Price": 7470, "Total Market": 410850, "Total Quantity": 55, "cost": 20, "id": 31117, "Price/Cost": 373.5}, {"Name": "Oddly Specific Coerthan Iron Ore", "Average Price": 0, "Total Market": 0, "Total Quantity": 0, "cost": 20, "id": 31118, "Price/Cost": 0.0}, {"Name": "Oddly Specific Mythrite Sand", "Average Price": 0, "Total Market": 0, "Total Quantity": 0, "cost": 20, "id": 31119, "Price/Cost": 0.0}, {"Name": "Oddly Specific Silver Ore", "Average Price": 0, "Total Market": 0, "Total Quantity": 0, "cost": 20, "id": 31120, "Price/Cost": 0.0}, {"Name": "Oddly Specific Gagana Skin", "Average Price": 0, "Total Market": 0, "Total Quantity": 0, "cost": 20, "id": 31121, "Price/Cost": 0.0}, {"Name": "Oddly Specific Fleece", "Average Price": 0, "Total Market": 0, "Total Quantity": 0, "cost": 20, "id": 31122, "Price/Cost": 0.0}, {"Name": "Oddly Specific Sap", "Average Price": 0, "Total Market": 0, "Total Quantity": 0, "cost": 20, "id": 31123, "Price/Cost": 0.0}, {"Name": "Oddly Specific Aloe", "Average Price": 0, "Total Market": 0, "Total Quantity": 0, "cost": 20, "id": 31124, "Price/Cost": 0.0}, {"Name": "Oddly Delicate Pine Log", "Average Price": 0, "Total Market": 0, "Total Quantity": 0, "cost": 30, "id": 31758, "Price/Cost": 0.0}, {"Name": "Oddly Delicate Silvergrace Ore", "Average Price": 0, "Total Market": 0, "Total Quantity": 0, "cost": 30, "id": 31759, "Price/Cost": 0.0}, {"Name": "Ballroom Etiquette - Next, Godliness", "Average Price": 294878, "Total Market": 4718054, "Total Quantity": 16, "cost": 1800, "id": 32829, "Price/Cost": 163.82111111111112}, {"Name": "Oddly Delicate Scheelite", "Average Price": 0, "Total Market": 0, "Total Quantity": 0, "cost": 30, "id": 31760, "Price/Cost": 0.0}, {"Name": "Oddly Delicate Raw Celestine", "Average Price": 0, "Total Market": 0, "Total Quantity": 0, "cost": 30, "id": 31761, "Price/Cost": 0.0}, {"Name": "Oddly Delicate Gazelle Hide", "Average Price": 0, "Total Market": 0, "Total Quantity": 0, "cost": 30, "id": 31762, "Price/Cost": 0.0}, {"Name": "Oddly Delicate Rhea", "Average Price": 0, "Total Market": 0, "Total Quantity": 0, "cost": 30, "id": 31763, "Price/Cost": 0.0}, {"Name": "Oddly Delicate Mistletoe", "Average Price": 0, "Total Market": 0, "Total Quantity": 0, "cost": 30, "id": 31764, "Price/Cost": 0.0}, {"Name": "Oddly Delicate Hammerhead Shark", "Average Price": 0, "Total Market": 0, "Total Quantity": 0, "cost": 30, "id": 31765, "Price/Cost": 0.0}, {"Name": "Ballroom Etiquette - Well Bread", "Average Price": 217444, "Total Market": 869776, "Total Quantity": 4, "cost": 900, "id": 30110, "Price/Cost": 241.60444444444445}, {"Name": "Modern Aesthetics - Modern Legend", "Average Price": 270787, "Total Market": 3520239, "Total Quantity": 13, "cost": 1800, "id": 28615, "Price/Cost": 150.43722222222223}, {"Name": "Modern Aesthetics - Controlled Chaos", "Average Price": 285443, "Total Market": 2568994, "Total Quantity": 9, "cost": 1800, "id": 30113, "Price/Cost": 158.57944444444445}, {"Name": "Modern Aesthetics - Saintly Style", "Average Price": 272975, "Total Market": 2456782, "Total Quantity": 9, "cost": 1800, "id": 31406, "Price/Cost": 151.65277777777777}, {"Name": "Miniature White Knight", "Average Price": 251369, "Total Market": 502739, "Total Quantity": 2, "cost": 1200, "id": 28622, "Price/Cost": 209.47416666666666}, {"Name": "Cerberpup", "Average Price": 209876, "Total Market": 1049380, "Total Quantity": 5, "cost": 1200, "id": 28628, "Price/Cost": 174.89666666666668}, {"Name": "Ufiti Horn", "Average Price": 666799, "Total Market": 3333996, "Total Quantity": 5, "cost": 8400, "id": 28917, "Price/Cost": 79.38083333333333}, {"Name": "Paissa Brat", "Average Price": 1761, "Total Market": 26417, "Total Quantity": 15, "cost": 800, "id": 13275, "Price/Cost": 2.20125}, {"Name": "Hunting Hawk", "Average Price": 11128, "Total Market": 89025, "Total Quantity": 8, "cost": 800, "id": 13279, "Price/Cost": 13.91}, {"Name": "Baby Brachiosaur", "Average Price": 3762, "Total Market": 45148, "Total Quantity": 12, "cost": 800, "id": 15441, "Price/Cost": 4.7025}, {"Name": "Machinist Barding", "Average Price": 395874, "Total Market": 791749, "Total Quantity": 2, "cost": 1200, "id": 29403, "Price/Cost": 329.895}, {"Name": "Safety in Numbers Orchestrion Roll", "Average Price": 0, "Total Market": 0, "Total Quantity": 0, "cost": 1200, "id": 28893, "Price/Cost": 0.0}, {"Name": "The Mendicant's Relish Orchestrion Roll", "Average Price": 0, "Total Market": 0, "Total Quantity": 0, "cost": 1200, "id": 30262, "Price/Cost": 0.0}, {"Name": "The Heavens' Ward Orchestrion Roll", "Average Price": 0, "Total Market": 0, "Total Quantity": 0, "cost": 1200, "id": 31675, "Price/Cost": 0.0}, {"Name": "Hearthward Orchestrion Roll", "Average Price": 0, "Total Market": 0, "Total Quantity": 0, "cost": 1200, "id": 33127, "Price/Cost": 0.0}, {"Name": "What Is Love? Orchestrion Roll", "Average Price": 0, "Total Market": 0, "Total Quantity": 0, "cost": 1200, "id": 33847, "Price/Cost": 0.0}, {"Name": "Megalotragus Horn", "Average Price": 504110, "Total Market": 2520550, "Total Quantity": 5, "cost": 8400, "id": 30862, "Price/Cost": 60.01309523809524}, {"Name": "Skyrise Orchestrion Roll", "Average Price": 0, "Total Market": 0, "Total Quantity": 0, "cost": 1200, "id": 33905, "Price/Cost": 0.0}, {"Name": "Unworthy Orchestrion Roll", "Average Price": 0, "Total Market": 0, "Total Quantity": 0, "cost": 1200, "id": 38647, "Price/Cost": 0.0}, {"Name": "Jewel Orchestrion Roll", "Average Price": 0, "Total Market": 0, "Total Quantity": 0, "cost": 600, "id": 17626, "Price/Cost": 0.0}, {"Name": "Paradise Found Orchestrion Roll", "Average Price": 0, "Total Market": 0, "Total Quantity": 0, "cost": 600, "id": 30259, "Price/Cost": 0.0}, {"Name": "Fealty Orchestrion Roll", "Average Price": 0, "Total Market": 0, "Total Quantity": 0, "cost": 600, "id": 30260, "Price/Cost": 0.0}, {"Name": "Stone and Steel Orchestrion Roll", "Average Price": 0, "Total Market": 0, "Total Quantity": 0, "cost": 600, "id": 30261, "Price/Cost": 0.0}, {"Name": "Order Yet Undeciphered Orchestrion Roll", "Average Price": 0, "Total Market": 0, "Total Quantity": 0, "cost": 600, "id": 30267, "Price/Cost": 0.0}, {"Name": "Freefall Orchestrion Roll", "Average Price": 215150, "Total Market": 215150, "Total Quantity": 1, "cost": 600, "id": 31674, "Price/Cost": 358.5833333333333}, {"Name": "Parasol", "Average Price": 291332, "Total Market": 1747995, "Total Quantity": 6, "cost": 1800, "id": 30269, "Price/Cost": 161.85111111111112}, {"Name": "Cheerful Checkered Parasol", "Average Price": 179998, "Total Market": 359996, "Total Quantity": 2, "cost": 1800, "id": 31325, "Price/Cost": 99.99888888888889}, {"Name": "Big Shell Whistle", "Average Price": 841247, "Total Market": 3364988, "Total Quantity": 4, "cost": 8400, "id": 32841, "Price/Cost": 100.14845238095238}, {"Name": "Pastoral Dot Parasol", "Average Price": 366249, "Total Market": 1464998, "Total Quantity": 4, "cost": 1800, "id": 33039, "Price/Cost": 203.47166666666666}, {"Name": "Sky Blue Parasol", "Average Price": 0, "Total Market": 0, "Total Quantity": 0, "cost": 900, "id": 30270, "Price/Cost": 0.0}, {"Name": "Calming Checkered Parasol", "Average Price": 199999, "Total Market": 199999, "Total Quantity": 1, "cost": 900, "id": 31324, "Price/Cost": 222.2211111111111}, {"Name": "Craftsman's Coverall Top", "Average Price": 397963, "Total Market": 397963, "Total Quantity": 1, "cost": 2200, "id": 28592, "Price/Cost": 180.89227272727274}, {"Name": "Craftsman's Singlet", "Average Price": 220000, "Total Market": 880000, "Total Quantity": 4, "cost": 2200, "id": 28594, "Price/Cost": 100.0}, {"Name": "Craftsman's Apron", "Average Price": 200001, "Total Market": 200001, "Total Quantity": 1, "cost": 2200, "id": 30052, "Price/Cost": 90.90954545454545}, {"Name": "Craftsman's Coverall Bottoms", "Average Price": 0, "Total Market": 0, "Total Quantity": 0, "cost": 2000, "id": 28593, "Price/Cost": 0.0}, {"Name": "Craftsman's Leather Trousers", "Average Price": 238377, "Total Market": 3098909, "Total Quantity": 13, "cost": 2000, "id": 30053, "Price/Cost": 119.1885}, {"Name": "Antelope Doe Horn", "Average Price": 927500, "Total Market": 927500, "Total Quantity": 1, "cost": 8400, "id": 33674, "Price/Cost": 110.41666666666667}, {"Name": "Craftsman's Leather Shoes", "Average Price": 209998, "Total Market": 1049993, "Total Quantity": 5, "cost": 2000, "id": 30054, "Price/Cost": 104.999}, {"Name": "Skyworker's Helmet", "Average Price": 0, "Total Market": 0, "Total Quantity": 0, "cost": 1200, "id": 32793, "Price/Cost": 0.0}, {"Name": "Skyworker's Singlet", "Average Price": 282029, "Total Market": 4512466, "Total Quantity": 16, "cost": 2200, "id": 32794, "Price/Cost": 128.195}, {"Name": "Skyworker's Gloves", "Average Price": 58999, "Total Market": 58999, "Total Quantity": 1, "cost": 1200, "id": 32795, "Price/Cost": 49.16583333333333}, {"Name": "Skyworker's Bottoms", "Average Price": 285320, "Total Market": 3423848, "Total Quantity": 12, "cost": 2000, "id": 32796, "Price/Cost": 142.66}, {"Name": "Skyworker's Boots", "Average Price": 0, "Total Market": 0, "Total Quantity": 0, "cost": 1200, "id": 32797, "Price/Cost": 0.0}, {"Name": "Stuffed Hraesvelgr", "Average Price": 0, "Total Market": 0, "Total Quantity": 0, "cost": 600, "id": 28141, "Price/Cost": 0.0}, {"Name": "Stuffed Estinien", "Average Price": 60060, "Total Market": 60060, "Total Quantity": 1, "cost": 600, "id": 30418, "Price/Cost": 100.1}, {"Name": "Stuffed Cait Sith", "Average Price": 65500, "Total Market": 65500, "Total Quantity": 1, "cost": 600, "id": 32213, "Price/Cost": 109.16666666666667}, {"Name": "Ballroom Etiquette - The Winsome Wallflower", "Average Price": 309749, "Total Market": 6504738, "Total Quantity": 21, "cost": 1800, "id": 28612, "Price/Cost": 172.08277777777778}, {"Name": "Huggable Gaelicat", "Average Price": 0, "Total Market": 0, "Total Quantity": 0, "cost": 250, "id": 30415, "Price/Cost": 0.0}, {"Name": "Lord Commander Portrait", "Average Price": 0, "Total Market": 0, "Total Quantity": 0, "cost": 900, "id": 28979, "Price/Cost": 0.0}, {"Name": "Azure Dragoon Portrait", "Average Price": 137056, "Total Market": 137056, "Total Quantity": 1, "cost": 900, "id": 28989, "Price/Cost": 152.28444444444443}, {"Name": "Garment Rack", "Average Price": 68899, "Total Market": 344495, "Total Quantity": 5, "cost": 350, "id": 28971, "Price/Cost": 196.8542857142857}, {"Name": "Fortemps Sofa", "Average Price": 62888, "Total Market": 125777, "Total Quantity": 2, "cost": 350, "id": 30417, "Price/Cost": 179.68}, {"Name": "Ishgardian Display Stand", "Average Price": 0, "Total Market": 0, "Total Quantity": 0, "cost": 350, "id": 30416, "Price/Cost": 0.0}, {"Name": "Imposing Ishgardian Shelf", "Average Price": 320448, "Total Market": 2884038, "Total Quantity": 9, "cost": 900, "id": 28140, "Price/Cost": 356.05333333333334}, {"Name": "Ishgardian Stove", "Average Price": 0, "Total Market": 0, "Total Quantity": 0, "cost": 350, "id": 32216, "Price/Cost": 0.0}, {"Name": "Apron Rack", "Average Price": 248261, "Total Market": 1737827, "Total Quantity": 7, "cost": 350, "id": 28995, "Price/Cost": 709.3171428571428}, {"Name": "Modern Mogseat", "Average Price": 0, "Total Market": 0, "Total Quantity": 0, "cost": 200, "id": 28964, "Price/Cost": 0.0}, {"Name": "Ballroom Etiquette - Intelligent Impressions", "Average Price": 359131, "Total Market": 1795655, "Total Quantity": 5, "cost": 1800, "id": 30111, "Price/Cost": 199.51722222222222}, {"Name": "Moogle Round Table", "Average Price": 0, "Total Market": 0, "Total Quantity": 0, "cost": 250, "id": 28963, "Price/Cost": 0.0}, {"Name": "Mandragora Table Chronometer", "Average Price": 0, "Total Market": 0, "Total Quantity": 0, "cost": 200, "id": 30413, "Price/Cost": 0.0}, {"Name": "Paissa Rug", "Average Price": 0, "Total Market": 0, "Total Quantity": 0, "cost": 200, "id": 30414, "Price/Cost": 0.0}, {"Name": "Skysteel Ingot", "Average Price": 0, "Total Market": 0, "Total Quantity": 0, "cost": 200, "id": 28906, "Price/Cost": 0.0}, {"Name": "Skysteel Cloth", "Average Price": 0, "Total Market": 0, "Total Quantity": 0, "cost": 200, "id": 28908, "Price/Cost": 0.0}, {"Name": "Skysteel Leather", "Average Price": 8744, "Total Market": 17489, "Total Quantity": 2, "cost": 200, "id": 28907, "Price/Cost": 43.72}, {"Name": "Gatherer's Guerdon Materia VII", "Average Price": 7190, "Total Market": 1107292, "Total Quantity": 154, "cost": 240, "id": 25191, "Price/Cost": 29.958333333333332}, {"Name": "Gatherer's Guerdon Materia VIII", "Average Price": 1089, "Total Market": 92611, "Total Quantity": 85, "cost": 300, "id": 26732, "Price/Cost": 3.63}, {"Name": "Ballroom Etiquette - Emphatic Elucidation", "Average Price": 194492, "Total Market": 1555943, "Total Quantity": 8, "cost": 1800, "id": 30112, "Price/Cost": 108.05111111111111}, {"Name": "Gatherer's Guile Materia VII", "Average Price": 1451, "Total Market": 130611, "Total Quantity": 90, "cost": 240, "id": 25192, "Price/Cost": 6.045833333333333}, {"Name": "Gatherer's Guile Materia VIII", "Average Price": 1118, "Total Market": 133117, "Total Quantity": 119, "cost": 300, "id": 26733, "Price/Cost": 3.7266666666666666}, {"Name": "Gatherer's Grasp Materia VII", "Average Price": 2557, "Total Market": 365782, "Total Quantity": 143, "cost": 240, "id": 25193, "Price/Cost": 10.654166666666667}, {"Name": "Gatherer's Grasp Materia VIII", "Average Price": 1056, "Total Market": 43315, "Total Quantity": 41, "cost": 300, "id": 26734, "Price/Cost": 3.52}, {"Name": "Craftsman's Competence Materia VII", "Average Price": 724, "Total Market": 146982, "Total Quantity": 203, "cost": 240, "id": 25194, "Price/Cost": 3.0166666666666666}, {"Name": "Craftsman's Competence Materia VIII", "Average Price": 1329, "Total Market": 138278, "Total Quantity": 104, "cost": 300, "id": 26735, "Price/Cost": 4.43}, {"Name": "Craftsman's Cunning Materia VII", "Average Price": 6438, "Total Market": 17159893, "Total Quantity": 2665, "cost": 240, "id": 25195, "Price/Cost": 26.825}, {"Name": "Craftsman's Cunning Materia VIII", "Average Price": 1181, "Total Market": 328584, "Total Quantity": 278, "cost": 300, "id": 26736, "Price/Cost": 3.9366666666666665}, {"Name": "Craftsman's Command Materia VII", "Average Price": 1545, "Total Market": 420496, "Total Quantity": 272, "cost": 240, "id": 25196, "Price/Cost": 6.4375}, {"Name": "Craftsman's Command Materia VIII", "Average Price": 996, "Total Market": 101660, "Total Quantity": 102, "cost": 300, "id": 26737, "Price/Cost": 3.32}]}