{"columns": ["Name", "Average Price", "Total Market", "Total Quantity", "id"], "items": [{"Name": "Lunar Adamantite Ore", "Average Price": 378, "Total Market": 18175, "Total Quantity": 48, "id": 36167}, {"Name": "Paldao Log", "Average Price": 345, "Total Market": 848345, "Total Quantity": 2453, "id": 37818}, {"Name": "Stonehard Water", "Average Price": 115, "Total Market": 13220, "Total Quantity": 114, "id": 36215}, {"Name": "Bayberry", "Average Price": 963, "Total Market": 4484104, "Total Quantity": 4652, "id": 37821}, {"Name": "Mornveil Tree Bark", "Average Price": 977, "Total Market": 1900293, "Total Quantity": 1944, "id": 38933}, {"Name": "Rhodium Sand", "Average Price": 0, "Total Market": 0, "Total Quantity": 0, "id": 36179}, {"Name": "Mempisang Log", "Average Price": 0, "Total Market": 0, "Total Quantity": 0, "id": 36195}, {"Name": "Raw Rutilated Quartz", "Average Price": 450, "Total Market": 1224397, "Total Quantity": 2717, "id": 37817}, {"Name": "Raw Zoisite", "Average Price": 667, "Total Market": 265144, "Total Quantity": 397, "id": 38934}, {"Name": "Ash Diatomite", "Average Price": 52, "Total Market": 7102, "Total Quantity": 136, "id": 37822}, {"Name": "Double-edged Herb", "Average Price": 0, "Total Market": 0, "Total Quantity": 0, "id": 36217}, {"Name": "Golden Cocoon", "Average Price": 292, "Total Market": 17538, "Total Quantity": 60, "id": 36207}, {"Name": "Haritaki", "Average Price": 833, "Total Market": 889391, "Total Quantity": 1067, "id": 37819}, {"Name": "Ilmenite", "Average Price": 1096, "Total Market": 5817559, "Total Quantity": 5306, "id": 37820}, {"Name": "Potent Spice", "Average Price": 410, "Total Market": 80005, "Total Quantity": 195, "id": 36214}, {"Name": "Raw Eblan Danburite", "Average Price": 243, "Total Market": 51096, "Total Quantity": 210, "id": 37279}, {"Name": "Rime Dolomite", "Average Price": 214, "Total Market": 27045, "Total Quantity": 126, "id": 36216}, {"Name": "Thavnairian Corn", "Average Price": 51, "Total Market": 12323, "Total Quantity": 239, "id": 37278}]}