{"columns": ["Name", "Average Price", "Total Market", "Total Quantity", "duration", "id", "level", "quantity", "Gil/Venture"], "items": [{"Name": "Double-edged Herb", "Average Price": 4, "Total Market": 8, "Total Quantity": 2, "duration": 60, "id": 36217, "level": 90, "quantity": 5, "Gil/Venture": 20}, {"Name": "Golden Cocoon", "Average Price": 0, "Total Market": 0, "Total Quantity": 0, "duration": 60, "id": 36207, "level": 90, "quantity": 5, "Gil/Venture": 0}, {"Name": "Mempisang Log", "Average Price": 25, "Total Market": 26245, "Total Quantity": 1019, "duration": 60, "id": 36195, "level": 90, "quantity": 5, "Gil/Venture": 125}, {"Name": "Potent Spice", "Average Price": 105, "Total Market": 23112, "Total Quantity": 219, "duration": 60, "id": 36214, "level": 90, "quantity": 5, "Gil/Venture": 525}, {"Name": "Alien Onion", "Average Price": 65, "Total Market": 16847, "Total Quantity": 258, "duration": 60, "id": 36097, "level": 90, "quantity": 20, "Gil/Venture": 1300}, {"Name": "AR-Caean Cotton Boll", "Average Price": 324, "Total Market": 291728, "Total Quantity": 898, "duration": 60, "id": 36206, "level": 89, "quantity": 20, "Gil/Venture": 6480}, {"Name": "Integral Log", "Average Price": 282, "Total Market": 597429, "Total Quantity": 2116, "duration": 60, "id": 36194, "level": 89, "quantity": 20, "Gil/Venture": 5640}, {"Name": "Elder Nutmeg Seeds", "Average Price": 134, "Total Market": 62151, "Total Quantity": 462, "duration": 60, "id": 36095, "level": 88, "quantity": 20, "Gil/Venture": 2680}, {"Name": "Sideritis Leaves", "Average Price": 384, "Total Market": 63135, "Total Quantity": 164, "duration": 60, "id": 36094, "level": 88, "quantity": 20, "Gil/Venture": 7680}, {"Name": "Giant Popoto", "Average Price": 600, "Total Market": 71451, "Total Quantity": 119, "duration": 60, "id": 36089, "level": 87, "quantity": 20, "Gil/Venture": 12000}, {"Name": "Sykon", "Average Price": 298, "Total Market": 17612, "Total Quantity": 59, "duration": 60, "id": 36096, "level": 87, "quantity": 20, "Gil/Venture": 5960}, {"Name": "Ironwood Log", "Average Price": 342, "Total Market": 182787, "Total Quantity": 534, "duration": 60, "id": 36193, "level": 86, "quantity": 20, "Gil/Venture": 6840}, {"Name": "Scarlet Moko Grass", "Average Price": 95, "Total Market": 9599, "Total Quantity": 100, "duration": 60, "id": 36205, "level": 86, "quantity": 20, "Gil/Venture": 1900}, {"Name": "Carrot of Happiness", "Average Price": 531, "Total Market": 54253, "Total Quantity": 102, "duration": 60, "id": 36090, "level": 85, "quantity": 30, "Gil/Venture": 15930}, {"Name": "Beet", "Average Price": 0, "Total Market": 0, "Total Quantity": 0, "duration": 60, "id": 36093, "level": 84, "quantity": 30, "Gil/Venture": 0}, {"Name": "Red Pine Log", "Average Price": 329, "Total Market": 179429, "Total Quantity": 544, "duration": 60, "id": 36192, "level": 84, "quantity": 30, "Gil/Venture": 9870}, {"Name": "Snow Flax", "Average Price": 18, "Total Market": 5843, "Total Quantity": 311, "duration": 60, "id": 36204, "level": 84, "quantity": 30, "Gil/Venture": 540}, {"Name": "Cucumber", "Average Price": 206, "Total Market": 8240, "Total Quantity": 40, "duration": 60, "id": 36091, "level": 83, "quantity": 30, "Gil/Venture": 6180}, {"Name": "Eblan Lentils", "Average Price": 0, "Total Market": 0, "Total Quantity": 0, "duration": 60, "id": 36092, "level": 83, "quantity": 30, "Gil/Venture": 0}, {"Name": "Coconut", "Average Price": 0, "Total Market": 0, "Total Quantity": 0, "duration": 60, "id": 36087, "level": 82, "quantity": 40, "Gil/Venture": 0}, {"Name": "Palm Log", "Average Price": 3, "Total Market": 30, "Total Quantity": 9, "duration": 60, "id": 36191, "level": 82, "quantity": 40, "Gil/Venture": 120}, {"Name": "Palm Syrup", "Average Price": 378, "Total Market": 197460, "Total Quantity": 522, "duration": 60, "id": 36086, "level": 82, "quantity": 40, "Gil/Venture": 15120}, {"Name": "Thavnairian Paprika", "Average Price": 0, "Total Market": 0, "Total Quantity": 0, "duration": 60, "id": 36098, "level": 82, "quantity": 40, "Gil/Venture": 0}, {"Name": "Thavnairian Perilla Leaf", "Average Price": 299, "Total Market": 14376, "Total Quantity": 48, "duration": 60, "id": 36085, "level": 82, "quantity": 40, "Gil/Venture": 11960}, {"Name": "Dark Hemp", "Average Price": 501, "Total Market": 220161, "Total Quantity": 439, "duration": 60, "id": 36202, "level": 81, "quantity": 40, "Gil/Venture": 20040}, {"Name": "Dark Rye", "Average Price": 343, "Total Market": 122562, "Total Quantity": 357, "duration": 60, "id": 36083, "level": 81, "quantity": 40, "Gil/Venture": 13720}, {"Name": "Horse Chestnut Log", "Average Price": 148, "Total Market": 18450, "Total Quantity": 124, "duration": 60, "id": 36190, "level": 81, "quantity": 40, "Gil/Venture": 5920}, {"Name": "Iceberg Lettuce", "Average Price": 0, "Total Market": 0, "Total Quantity": 0, "duration": 60, "id": 36088, "level": 81, "quantity": 40, "Gil/Venture": 0}, {"Name": "Lemonette", "Average Price": 727, "Total Market": 165107, "Total Quantity": 227, "duration": 60, "id": 27835, "level": 80, "quantity": 9, "Gil/Venture": 6543}, {"Name": "Lignum Vitae Log", "Average Price": 275, "Total Market": 38281, "Total Quantity": 139, "duration": 60, "id": 27687, "level": 80, "quantity": 50, "Gil/Venture": 13750}, {"Name": "Ethereal Cocoon", "Average Price": 0, "Total Market": 0, "Total Quantity": 0, "duration": 60, "id": 27761, "level": 80, "quantity": 9, "Gil/Venture": 0}, {"Name": "Sandalwood Log", "Average Price": 0, "Total Market": 0, "Total Quantity": 0, "duration": 60, "id": 27688, "level": 80, "quantity": 9, "Gil/Venture": 0}, {"Name": "Sandalwood Sap", "Average Price": 0, "Total Market": 0, "Total Quantity": 0, "duration": 60, "id": 28716, "level": 80, "quantity": 9, "Gil/Venture": 0}, {"Name": "Duskblooms", "Average Price": 0, "Total Market": 0, "Total Quantity": 0, "duration": 60, "id": 29974, "level": 80, "quantity": 9, "Gil/Venture": 0}, {"Name": "Imperial Fern", "Average Price": 0, "Total Market": 0, "Total Quantity": 0, "duration": 60, "id": 29978, "level": 80, "quantity": 9, "Gil/Venture": 0}, {"Name": "Merbau Log", "Average Price": 0, "Total Market": 0, "Total Quantity": 0, "duration": 60, "id": 29972, "level": 80, "quantity": 9, "Gil/Venture": 0}, {"Name": "Tender Dill", "Average Price": 0, "Total Market": 0, "Total Quantity": 0, "duration": 60, "id": 30485, "level": 80, "quantity": 9, "Gil/Venture": 0}, {"Name": "Raindrop Cotton Boll", "Average Price": 0, "Total Market": 0, "Total Quantity": 0, "duration": 60, "id": 32953, "level": 80, "quantity": 8, "Gil/Venture": 0}, {"Name": "Silver Beech Log", "Average Price": 0, "Total Market": 0, "Total Quantity": 0, "duration": 60, "id": 32950, "level": 80, "quantity": 8, "Gil/Venture": 0}, {"Name": "Wattle Petribark", "Average Price": 0, "Total Market": 0, "Total Quantity": 0, "duration": 60, "id": 32954, "level": 80, "quantity": 8, "Gil/Venture": 0}, {"Name": "Dwarven Cotton Boll", "Average Price": 0, "Total Market": 0, "Total Quantity": 0, "duration": 50, "id": 27759, "level": 79, "quantity": 50, "Gil/Venture": 0}, {"Name": "Light Gerbera", "Average Price": 232, "Total Market": 256402, "Total Quantity": 1101, "duration": 50, "id": 27785, "level": 79, "quantity": 50, "Gil/Venture": 11600}, {"Name": "Tiger Lily", "Average Price": 348, "Total Market": 26479, "Total Quantity": 76, "duration": 50, "id": 27784, "level": 79, "quantity": 50, "Gil/Venture": 17400}, {"Name": "Bomba Rice", "Average Price": 0, "Total Market": 0, "Total Quantity": 0, "duration": 50, "id": 27830, "level": 78, "quantity": 50, "Gil/Venture": 0}, {"Name": "Coffee Beans", "Average Price": 0, "Total Market": 0, "Total Quantity": 0, "duration": 50, "id": 27837, "level": 78, "quantity": 50, "Gil/Venture": 0}, {"Name": "Harcot", "Average Price": 250, "Total Market": 3000, "Total Quantity": 12, "duration": 50, "id": 27819, "level": 78, "quantity": 50, "Gil/Venture": 12500}, {"Name": "Lime Basil", "Average Price": 263, "Total Market": 11046, "Total Quantity": 42, "duration": 50, "id": 27783, "level": 78, "quantity": 50, "Gil/Venture": 13150}, {"Name": "Mist Spinach", "Average Price": 64, "Total Market": 2240, "Total Quantity": 35, "duration": 50, "id": 27828, "level": 78, "quantity": 9, "Gil/Venture": 576}, {"Name": "Fernleaf Lavender", "Average Price": 327, "Total Market": 22950, "Total Quantity": 70, "duration": 50, "id": 27780, "level": 77, "quantity": 50, "Gil/Venture": 16350}, {"Name": "Amber Cloves", "Average Price": 254, "Total Market": 5598, "Total Quantity": 22, "duration": 50, "id": 27821, "level": 76, "quantity": 50, "Gil/Venture": 12700}, {"Name": "Russet Popoto", "Average Price": 0, "Total Market": 0, "Total Quantity": 0, "duration": 50, "id": 27822, "level": 76, "quantity": 9, "Gil/Venture": 0}, {"Name": "Sandteak Log", "Average Price": 0, "Total Market": 0, "Total Quantity": 0, "duration": 50, "id": 27686, "level": 76, "quantity": 50, "Gil/Venture": 0}, {"Name": "Sweet Alyssum", "Average Price": 277, "Total Market": 64114, "Total Quantity": 231, "duration": 50, "id": 27779, "level": 76, "quantity": 50, "Gil/Venture": 13850}, {"Name": "Creamtop Mushroom", "Average Price": 179, "Total Market": 4851, "Total Quantity": 27, "duration": 50, "id": 27829, "level": 75, "quantity": 50, "Gil/Venture": 8950}, {"Name": "Gianthive Chip", "Average Price": 796, "Total Market": 165578, "Total Quantity": 208, "duration": 50, "id": 27834, "level": 75, "quantity": 50, "Gil/Venture": 39800}, {"Name": "Royal Grapes", "Average Price": 417, "Total Market": 53800, "Total Quantity": 129, "duration": 50, "id": 27826, "level": 75, "quantity": 50, "Gil/Venture": 20850}, {"Name": "Peppermint", "Average Price": 0, "Total Market": 0, "Total Quantity": 0, "duration": 50, "id": 27836, "level": 74, "quantity": 9, "Gil/Venture": 0}, {"Name": "Pixie Floss Boll", "Average Price": 0, "Total Market": 0, "Total Quantity": 0, "duration": 50, "id": 27753, "level": 74, "quantity": 50, "Gil/Venture": 0}, {"Name": "White Ash Log", "Average Price": 197, "Total Market": 4749, "Total Quantity": 24, "duration": 50, "id": 27685, "level": 74, "quantity": 50, "Gil/Venture": 9850}, {"Name": "Upland Wheat", "Average Price": 266, "Total Market": 53052, "Total Quantity": 199, "duration": 50, "id": 27832, "level": 73, "quantity": 50, "Gil/Venture": 13300}, {"Name": "Broad Beans", "Average Price": 0, "Total Market": 0, "Total Quantity": 0, "duration": 50, "id": 27833, "level": 72, "quantity": 9, "Gil/Venture": 0}, {"Name": "Garden Beet", "Average Price": 472, "Total Market": 842094, "Total Quantity": 1782, "duration": 50, "id": 27824, "level": 72, "quantity": 50, "Gil/Venture": 23600}, {"Name": "Iridescent Cocoon", "Average Price": 498, "Total Market": 5478, "Total Quantity": 11, "duration": 50, "id": 27750, "level": 72, "quantity": 50, "Gil/Venture": 24900}, {"Name": "Miracle Apple Log", "Average Price": 102, "Total Market": 1224, "Total Quantity": 12, "duration": 50, "id": 27684, "level": 72, "quantity": 50, "Gil/Venture": 5100}, {"Name": "Blood Tomato", "Average Price": 273, "Total Market": 11500, "Total Quantity": 42, "duration": 50, "id": 27825, "level": 71, "quantity": 50, "Gil/Venture": 13650}, {"Name": "Bright Flax", "Average Price": 0, "Total Market": 0, "Total Quantity": 0, "duration": 50, "id": 27747, "level": 71, "quantity": 50, "Gil/Venture": 0}, {"Name": "Curly Parsley", "Average Price": 0, "Total Market": 0, "Total Quantity": 0, "duration": 50, "id": 27823, "level": 71, "quantity": 50, "Gil/Venture": 0}, {"Name": "Frantoio", "Average Price": 1201, "Total Market": 16820, "Total Quantity": 14, "duration": 50, "id": 27820, "level": 71, "quantity": 50, "Gil/Venture": 60050}, {"Name": "Pixie Apple", "Average Price": 0, "Total Market": 0, "Total Quantity": 0, "duration": 50, "id": 27831, "level": 71, "quantity": 50, "Gil/Venture": 0}, {"Name": "Purple Carrot", "Average Price": 0, "Total Market": 0, "Total Quantity": 0, "duration": 50, "id": 27818, "level": 71, "quantity": 50, "Gil/Venture": 0}, {"Name": "White Oak Branch", "Average Price": 0, "Total Market": 0, "Total Quantity": 0, "duration": 50, "id": 27816, "level": 71, "quantity": 50, "Gil/Venture": 0}, {"Name": "White Oak Log", "Average Price": 15, "Total Market": 870, "Total Quantity": 58, "duration": 50, "id": 27683, "level": 71, "quantity": 50, "Gil/Venture": 750}, {"Name": "Othardian Plum", "Average Price": 0, "Total Market": 0, "Total Quantity": 0, "duration": 50, "id": 19852, "level": 70, "quantity": 50, "Gil/Venture": 0}, {"Name": "Zelkova Log", "Average Price": 166, "Total Market": 7151, "Total Quantity": 43, "duration": 50, "id": 19933, "level": 70, "quantity": 50, "Gil/Venture": 8300}, {"Name": "Azim Cotton Boll", "Average Price": 0, "Total Market": 0, "Total Quantity": 0, "duration": 50, "id": 21086, "level": 70, "quantity": 50, "Gil/Venture": 0}, {"Name": "Hallowed Basil", "Average Price": 0, "Total Market": 0, "Total Quantity": 0, "duration": 50, "id": 19918, "level": 70, "quantity": 50, "Gil/Venture": 0}, {"Name": "Rhea", "Average Price": 0, "Total Market": 0, "Total Quantity": 0, "duration": 50, "id": 19991, "level": 70, "quantity": 50, "Gil/Venture": 0}, {"Name": "Torreya Log", "Average Price": 589, "Total Market": 52446, "Total Quantity": 89, "duration": 50, "id": 19934, "level": 70, "quantity": 50, "Gil/Venture": 29450}, {"Name": "Black Willow Log", "Average Price": 0, "Total Market": 0, "Total Quantity": 0, "duration": 50, "id": 22419, "level": 70, "quantity": 50, "Gil/Venture": 0}, {"Name": "Hardened Veteran Tree Sap", "Average Price": 0, "Total Market": 0, "Total Quantity": 0, "duration": 50, "id": 23180, "level": 70, "quantity": 50, "Gil/Venture": 0}, {"Name": "Hingan Flax", "Average Price": 0, "Total Market": 0, "Total Quantity": 0, "duration": 50, "id": 22420, "level": 70, "quantity": 50, "Gil/Venture": 0}, {"Name": "Night Pepper", "Average Price": 0, "Total Market": 0, "Total Quantity": 0, "duration": 50, "id": 27827, "level": 70, "quantity": 50, "Gil/Venture": 0}, {"Name": "Urunday Log", "Average Price": 0, "Total Market": 0, "Total Quantity": 0, "duration": 50, "id": 24242, "level": 70, "quantity": 50, "Gil/Venture": 0}, {"Name": "Yanxian Cotton Boll", "Average Price": 0, "Total Market": 0, "Total Quantity": 0, "duration": 50, "id": 24243, "level": 70, "quantity": 50, "Gil/Venture": 0}]}