{"columns": ["Name", "Average Price", "Total Market", "Total Quantity", "cost", "id", "Price/Cost"], "items": [{"Name": "Gatherer's Guerdon Materia X", "Average Price": 16454, "Total Market": 1793510, "Total Quantity": 109, "cost": 500, "id": 33935, "Price/Cost": 32.908}, {"Name": "Gatherer's Guile Materia X", "Average Price": 4988, "Total Market": 1711082, "Total Quantity": 343, "cost": 500, "id": 33936, "Price/Cost": 9.976}, {"Name": "Gatherer's Grasp Materia X", "Average Price": 1554, "Total Market": 76146, "Total Quantity": 49, "cost": 500, "id": 33937, "Price/Cost": 3.108}, {"Name": "Moonlight Aethersand", "Average Price": 1456, "Total Market": 3161800, "Total Quantity": 2171, "cost": 100, "id": 36223, "Price/Cost": 14.56}, {"Name": "Endstone Aethersand", "Average Price": 90, "Total Market": 10653, "Total Quantity": 118, "cost": 200, "id": 36224, "Price/Cost": 0.45}, {"Name": "Endwood Aethersand", "Average Price": 3, "Total Market": 264, "Total Quantity": 88, "cost": 200, "id": 36225, "Price/Cost": 0.015}, {"Name": "Endtide Aethersand", "Average Price": 0, "Total Market": 0, "Total Quantity": 0, "cost": 200, "id": 36226, "Price/Cost": 0.0}, {"Name": "Earthbreak Aethersand", "Average Price": 1274, "Total Market": 2315308, "Total Quantity": 1817, "cost": 300, "id": 38936, "Price/Cost": 4.246666666666667}, {"Name": "Mackerel Strip", "Average Price": 0, "Total Market": 0, "Total Quantity": 0, "cost": 5, "id": 36593, "Price/Cost": 0.0}, {"Name": "Mayfly", "Average Price": 0, "Total Market": 0, "Total Quantity": 0, "cost": 5, "id": 36591, "Price/Cost": 0.0}, {"Name": "Stardust", "Average Price": 0, "Total Market": 0, "Total Quantity": 0, "cost": 5, "id": 36597, "Price/Cost": 0.0}]}