{"columns": ["Name", "Average Price", "Total Market", "Total Quantity", "duration", "id", "level", "quantity", "Gil/Venture"], "items": [{"Name": "Stonehard Water", "Average Price": 0, "Total Market": 0, "Total Quantity": 0, "duration": 60, "id": 36215, "level": 90, "quantity": 7, "Gil/Venture": 0}, {"Name": "Lunar Adamantite Ore", "Average Price": 452, "Total Market": 189026, "Total Quantity": 418, "duration": 60, "id": 36167, "level": 90, "quantity": 7, "Gil/Venture": 3164}, {"Name": "Rhodium Sand", "Average Price": 0, "Total Market": 0, "Total Quantity": 0, "duration": 60, "id": 36179, "level": 90, "quantity": 7, "Gil/Venture": 0}, {"Name": "Rime Dolomite", "Average Price": 248, "Total Market": 146352, "Total Quantity": 590, "duration": 60, "id": 36216, "level": 90, "quantity": 7, "Gil/Venture": 1736}, {"Name": "Raw Eblan Danburite", "Average Price": 6, "Total Market": 5081, "Total Quantity": 772, "duration": 60, "id": 37279, "level": 90, "quantity": 7, "Gil/Venture": 42}, {"Name": "Raw Star Quartz", "Average Price": 130, "Total Market": 431337, "Total Quantity": 3312, "duration": 60, "id": 36178, "level": 90, "quantity": 30, "Gil/Venture": 3900}, {"Name": "Chondrite", "Average Price": 175, "Total Market": 1103641, "Total Quantity": 6281, "duration": 60, "id": 36166, "level": 89, "quantity": 30, "Gil/Venture": 5250}, {"Name": "Ambrosial Water", "Average Price": 209, "Total Market": 923763, "Total Quantity": 4417, "duration": 60, "id": 36263, "level": 88, "quantity": 40, "Gil/Venture": 8360}, {"Name": "Annite", "Average Price": 144, "Total Market": 481263, "Total Quantity": 3321, "duration": 60, "id": 36181, "level": 87, "quantity": 40, "Gil/Venture": 5760}, {"Name": "Manganese Ore", "Average Price": 73, "Total Market": 194066, "Total Quantity": 2643, "duration": 60, "id": 36165, "level": 86, "quantity": 40, "Gil/Venture": 2920}, {"Name": "Raw Blue Zircon", "Average Price": 6, "Total Market": 3058, "Total Quantity": 447, "duration": 60, "id": 36177, "level": 86, "quantity": 40, "Gil/Venture": 240}, {"Name": "Bismuth Ore", "Average Price": 214, "Total Market": 649547, "Total Quantity": 3028, "duration": 60, "id": 36164, "level": 85, "quantity": 40, "Gil/Venture": 8560}, {"Name": "Eblan Alumen", "Average Price": 221, "Total Market": 311643, "Total Quantity": 1408, "duration": 60, "id": 36241, "level": 84, "quantity": 50, "Gil/Venture": 11050}, {"Name": "Phrygian Gold Ore", "Average Price": 213, "Total Market": 370065, "Total Quantity": 1735, "duration": 60, "id": 36176, "level": 83, "quantity": 50, "Gil/Venture": 10650}, {"Name": "High Durium Ore", "Average Price": 373, "Total Market": 322971, "Total Quantity": 865, "duration": 60, "id": 36163, "level": 82, "quantity": 50, "Gil/Venture": 18650}, {"Name": "Pewter Ore", "Average Price": 366, "Total Market": 276617, "Total Quantity": 755, "duration": 60, "id": 36175, "level": 82, "quantity": 50, "Gil/Venture": 18300}, {"Name": "Chloroschist", "Average Price": 115, "Total Market": 42874, "Total Quantity": 371, "duration": 60, "id": 36180, "level": 81, "quantity": 50, "Gil/Venture": 5750}, {"Name": "High Durium Sand", "Average Price": 240, "Total Market": 155425, "Total Quantity": 645, "duration": 60, "id": 36162, "level": 81, "quantity": 50, "Gil/Venture": 12000}, {"Name": "Raw Ametrine", "Average Price": 39, "Total Market": 43487, "Total Quantity": 1101, "duration": 60, "id": 36174, "level": 81, "quantity": 50, "Gil/Venture": 1950}, {"Name": "Sharlayan Rock Salt", "Average Price": 553, "Total Market": 682913, "Total Quantity": 1234, "duration": 60, "id": 36084, "level": 81, "quantity": 50, "Gil/Venture": 27650}, {"Name": "Dimythrite Ore", "Average Price": 5298, "Total Market": 18010238, "Total Quantity": 3399, "duration": 60, "id": 27703, "level": 80, "quantity": 50, "Gil/Venture": 264900}, {"Name": "Raw Onyx", "Average Price": 955, "Total Market": 267617, "Total Quantity": 280, "duration": 60, "id": 27731, "level": 80, "quantity": 9, "Gil/Venture": 8595}, {"Name": "Beryllium Ore", "Average Price": 4185, "Total Market": 276232, "Total Quantity": 66, "duration": 60, "id": 28717, "level": 80, "quantity": 9, "Gil/Venture": 37665}, {"Name": "Prismstone", "Average Price": 992, "Total Market": 118158, "Total Quantity": 119, "duration": 60, "id": 27705, "level": 80, "quantity": 9, "Gil/Venture": 8928}, {"Name": "Tungsten Ore", "Average Price": 256, "Total Market": 132288, "Total Quantity": 515, "duration": 60, "id": 27704, "level": 80, "quantity": 9, "Gil/Venture": 2304}, {"Name": "Ashen Alumen", "Average Price": 1043, "Total Market": 278730, "Total Quantity": 267, "duration": 60, "id": 29976, "level": 80, "quantity": 9, "Gil/Venture": 9387}, {"Name": "Brashgold Ore", "Average Price": 1560, "Total Market": 238808, "Total Quantity": 153, "duration": 60, "id": 30486, "level": 80, "quantity": 9, "Gil/Venture": 14040}, {"Name": "Fireheart Cobalt", "Average Price": 1500, "Total Market": 100500, "Total Quantity": 67, "duration": 60, "id": 29968, "level": 80, "quantity": 9, "Gil/Venture": 13500}, {"Name": "Purpure Shell Chip", "Average Price": 999, "Total Market": 210965, "Total Quantity": 211, "duration": 60, "id": 29970, "level": 80, "quantity": 9, "Gil/Venture": 8991}, {"Name": "Dolomite", "Average Price": 0, "Total Market": 0, "Total Quantity": 0, "duration": 60, "id": 32951, "level": 80, "quantity": 9, "Gil/Venture": 0}, {"Name": "Hard Water", "Average Price": 0, "Total Market": 0, "Total Quantity": 0, "duration": 60, "id": 32955, "level": 80, "quantity": 9, "Gil/Venture": 0}, {"Name": "Solstice Stone", "Average Price": 0, "Total Market": 0, "Total Quantity": 0, "duration": 60, "id": 32952, "level": 80, "quantity": 9, "Gil/Venture": 0}, {"Name": "Dimythrite Sand", "Average Price": 221, "Total Market": 378408, "Total Quantity": 1706, "duration": 50, "id": 27702, "level": 79, "quantity": 50, "Gil/Venture": 11050}, {"Name": "Raw Petalite", "Average Price": 144, "Total Market": 92027, "Total Quantity": 636, "duration": 50, "id": 27730, "level": 78, "quantity": 9, "Gil/Venture": 1296}, {"Name": "Underground Spring Water", "Average Price": 232, "Total Market": 606054, "Total Quantity": 2610, "duration": 50, "id": 27782, "level": 78, "quantity": 50, "Gil/Venture": 11600}, {"Name": "Titancopper Ore", "Average Price": 115, "Total Market": 54663, "Total Quantity": 474, "duration": 50, "id": 27701, "level": 77, "quantity": 50, "Gil/Venture": 5750}, {"Name": "Extra Effervescent Water", "Average Price": 147, "Total Market": 60210, "Total Quantity": 409, "duration": 50, "id": 27776, "level": 76, "quantity": 50, "Gil/Venture": 7350}, {"Name": "Raw Triplite", "Average Price": 49, "Total Market": 15389, "Total Quantity": 311, "duration": 50, "id": 27729, "level": 76, "quantity": 9, "Gil/Venture": 441}, {"Name": "Titancopper Sand", "Average Price": 43, "Total Market": 17300, "Total Quantity": 398, "duration": 50, "id": 27700, "level": 76, "quantity": 50, "Gil/Venture": 2150}, {"Name": "Volcanic Tuff", "Average Price": 376, "Total Market": 184932, "Total Quantity": 491, "duration": 50, "id": 27803, "level": 76, "quantity": 50, "Gil/Venture": 18800}, {"Name": "Manasilver Sand", "Average Price": 61, "Total Market": 36097, "Total Quantity": 584, "duration": 50, "id": 27699, "level": 75, "quantity": 50, "Gil/Venture": 3050}, {"Name": "Bluespirit Ore", "Average Price": 290, "Total Market": 206248, "Total Quantity": 709, "duration": 50, "id": 27698, "level": 74, "quantity": 50, "Gil/Venture": 14500}, {"Name": "Raw Lazurite", "Average Price": 27, "Total Market": 2738, "Total Quantity": 98, "duration": 50, "id": 27728, "level": 74, "quantity": 9, "Gil/Venture": 243}, {"Name": "Highland Spring Water", "Average Price": 178, "Total Market": 199609, "Total Quantity": 1120, "duration": 50, "id": 27968, "level": 73, "quantity": 50, "Gil/Venture": 8900}, {"Name": "Raw Diaspore", "Average Price": 124, "Total Market": 26214, "Total Quantity": 210, "duration": 50, "id": 27727, "level": 72, "quantity": 50, "Gil/Venture": 6200}, {"Name": "Truegold Ore", "Average Price": 253, "Total Market": 440251, "Total Quantity": 1734, "duration": 50, "id": 27697, "level": 72, "quantity": 50, "Gil/Venture": 12650}, {"Name": "Hard Mudstone", "Average Price": 62, "Total Market": 38273, "Total Quantity": 611, "duration": 50, "id": 27801, "level": 71, "quantity": 50, "Gil/Venture": 3100}, {"Name": "Truegold Sand", "Average Price": 196, "Total Market": 403059, "Total Quantity": 2051, "duration": 50, "id": 27696, "level": 71, "quantity": 50, "Gil/Venture": 9800}, {"Name": "Molybdenum Ore", "Average Price": 280, "Total Market": 813595, "Total Quantity": 2898, "duration": 50, "id": 19957, "level": 70, "quantity": 50, "Gil/Venture": 14000}, {"Name": "Raw Rhodonite", "Average Price": 912, "Total Market": 370514, "Total Quantity": 406, "duration": 50, "id": 19973, "level": 70, "quantity": 9, "Gil/Venture": 8208}, {"Name": "Chromite Ore", "Average Price": 1500, "Total Market": 30000, "Total Quantity": 20, "duration": 50, "id": 19959, "level": 70, "quantity": 9, "Gil/Venture": 13500}, {"Name": "Gyr Abanian Spring Water", "Average Price": 124, "Total Market": 2604, "Total Quantity": 21, "duration": 50, "id": 21085, "level": 70, "quantity": 9, "Gil/Venture": 1116}, {"Name": "Palladium Ore", "Average Price": 0, "Total Market": 0, "Total Quantity": 0, "duration": 50, "id": 19958, "level": 70, "quantity": 9, "Gil/Venture": 0}, {"Name": "Azim Spring Water", "Average Price": 0, "Total Market": 0, "Total Quantity": 0, "duration": 50, "id": 24255, "level": 70, "quantity": 9, "Gil/Venture": 0}, {"Name": "Coarse Saltpeter", "Average Price": 0, "Total Market": 0, "Total Quantity": 0, "duration": 50, "id": 27954, "level": 70, "quantity": 50, "Gil/Venture": 0}, {"Name": "Hawk's Eye", "Average Price": 1413, "Total Market": 231858, "Total Quantity": 164, "duration": 50, "id": 23179, "level": 70, "quantity": 9, "Gil/Venture": 12717}, {"Name": "Nightsteel Ore", "Average Price": 0, "Total Market": 0, "Total Quantity": 0, "duration": 50, "id": 22417, "level": 70, "quantity": 9, "Gil/Venture": 0}, {"Name": "Raw Hematite", "Average Price": 10, "Total Market": 750, "Total Quantity": 75, "duration": 50, "id": 27726, "level": 70, "quantity": 9, "Gil/Venture": 90}, {"Name": "Silvergrace Ore", "Average Price": 789, "Total Market": 19725, "Total Quantity": 25, "duration": 50, "id": 22418, "level": 70, "quantity": 9, "Gil/Venture": 7101}, {"Name": "Yellow Alumen", "Average Price": 267, "Total Market": 288280, "Total Quantity": 1078, "duration": 50, "id": 27817, "level": 70, "quantity": 50, "Gil/Venture": 13350}, {"Name": "Evergleam Ore", "Average Price": 0, "Total Market": 0, "Total Quantity": 0, "duration": 50, "id": 24241, "level": 70, "quantity": 9, "Gil/Venture": 0}, {"Name": "Gyr Abanian Ore", "Average Price": 0, "Total Market": 0, "Total Quantity": 0, "duration": 50, "id": 24240, "level": 70, "quantity": 50, "Gil/Venture": 0}]}