{"columns": ["Name", "Average Price", "Total Market", "Total Quantity", "cost", "id", "Price/Cost"], "items": [{"Name": "Ruby Red Dye", "Average Price": 13252, "Total Market": 5738279, "Total Quantity": 433, "cost": 500, "id": 30116, "Price/Cost": 26.504}, {"Name": "Cherry Pink Dye", "Average Price": 10123, "Total Market": 2267712, "Total Quantity": 224, "cost": 500, "id": 30117, "Price/Cost": 20.246}, {"Name": "Canary Yellow Dye", "Average Price": 10033, "Total Market": 290980, "Total Quantity": 29, "cost": 500, "id": 30118, "Price/Cost": 20.066}, {"Name": "Vanilla Yellow Dye", "Average Price": 5984, "Total Market": 137642, "Total Quantity": 23, "cost": 500, "id": 30119, "Price/Cost": 11.968}, {"Name": "Dragoon Blue Dye", "Average Price": 12863, "Total Market": 411647, "Total Quantity": 32, "cost": 500, "id": 30120, "Price/Cost": 25.726}, {"Name": "Turquoise Blue Dye", "Average Price": 13955, "Total Market": 2609753, "Total Quantity": 187, "cost": 500, "id": 30121, "Price/Cost": 27.91}, {"Name": "Gunmetal Black Dye", "Average Price": 36623, "Total Market": 6738701, "Total Quantity": 184, "cost": 2500, "id": 30122, "Price/Cost": 14.6492}, {"Name": "Pearl White Dye", "Average Price": 37633, "Total Market": 7526686, "Total Quantity": 200, "cost": 2500, "id": 30123, "Price/Cost": 15.0532}, {"Name": "Metallic Brass Dye", "Average Price": 39693, "Total Market": 1151124, "Total Quantity": 29, "cost": 2500, "id": 30124, "Price/Cost": 15.8772}, {"Name": "Craftsman's Cunning Materia X", "Average Price": 5680, "Total Market": 6714389, "Total Quantity": 1182, "cost": 1500, "id": 33939, "Price/Cost": 3.7866666666666666}, {"Name": "Craftsman's Command Materia IX", "Average Price": 9764, "Total Market": 65755398, "Total Quantity": 6734, "cost": 750, "id": 33927, "Price/Cost": 13.018666666666666}, {"Name": "Craftsman's Command Materia X", "Average Price": 24418, "Total Market": 93621841, "Total Quantity": 3834, "cost": 1500, "id": 33940, "Price/Cost": 16.278666666666666}, {"Name": "Gatherer's Guerdon Materia IX", "Average Price": 21849, "Total Market": 105469630, "Total Quantity": 4827, "cost": 750, "id": 33922, "Price/Cost": 29.132}, {"Name": "Gatherer's Guerdon Materia X", "Average Price": 18624, "Total Market": 39595711, "Total Quantity": 2126, "cost": 1500, "id": 33935, "Price/Cost": 12.416}, {"Name": "Gatherer's Guile Materia IX", "Average Price": 15073, "Total Market": 69384121, "Total Quantity": 4603, "cost": 750, "id": 33923, "Price/Cost": 20.097333333333335}, {"Name": "Gatherer's Guile Materia X", "Average Price": 9386, "Total Market": 27390558, "Total Quantity": 2918, "cost": 1500, "id": 33936, "Price/Cost": 6.257333333333333}, {"Name": "Gatherer's Grasp Materia IX", "Average Price": 14745, "Total Market": 54898959, "Total Quantity": 3723, "cost": 750, "id": 33924, "Price/Cost": 19.66}, {"Name": "Gatherer's Grasp Materia X", "Average Price": 1714, "Total Market": 1825626, "Total Quantity": 1065, "cost": 1500, "id": 33937, "Price/Cost": 1.1426666666666667}, {"Name": "Craftsman's Competence Materia IX", "Average Price": 4976, "Total Market": 16700137, "Total Quantity": 3356, "cost": 750, "id": 33925, "Price/Cost": 6.634666666666667}, {"Name": "Craftsman's Competence Materia X", "Average Price": 14545, "Total Market": 24262260, "Total Quantity": 1668, "cost": 1500, "id": 33938, "Price/Cost": 9.696666666666667}, {"Name": "Craftsman's Cunning Materia IX", "Average Price": 11899, "Total Market": 34924643, "Total Quantity": 2935, "cost": 750, "id": 33926, "Price/Cost": 15.865333333333334}]}