{"columns": ["Name", "Average Price", "Total Market", "Total Quantity", "cost", "id", "Price/Cost"], "items": [{"Name": "Ruby Red Dye", "Average Price": 10595, "Total Market": 4725754, "Total Quantity": 446, "cost": 500, "id": 30116, "Price/Cost": 21.19}, {"Name": "Cherry Pink Dye", "Average Price": 8919, "Total Market": 2087131, "Total Quantity": 234, "cost": 500, "id": 30117, "Price/Cost": 17.838}, {"Name": "Canary Yellow Dye", "Average Price": 13190, "Total Market": 171471, "Total Quantity": 13, "cost": 500, "id": 30118, "Price/Cost": 26.38}, {"Name": "Vanilla Yellow Dye", "Average Price": 5488, "Total Market": 109762, "Total Quantity": 20, "cost": 500, "id": 30119, "Price/Cost": 10.976}, {"Name": "Dragoon Blue Dye", "Average Price": 12430, "Total Market": 957175, "Total Quantity": 77, "cost": 500, "id": 30120, "Price/Cost": 24.86}, {"Name": "Turquoise Blue Dye", "Average Price": 10773, "Total Market": 463274, "Total Quantity": 43, "cost": 500, "id": 30121, "Price/Cost": 21.546}, {"Name": "Gunmetal Black Dye", "Average Price": 33144, "Total Market": 9910194, "Total Quantity": 299, "cost": 2500, "id": 30122, "Price/Cost": 13.2576}, {"Name": "Pearl White Dye", "Average Price": 48762, "Total Market": 9069838, "Total Quantity": 186, "cost": 2500, "id": 30123, "Price/Cost": 19.5048}, {"Name": "Metallic Brass Dye", "Average Price": 35768, "Total Market": 3076074, "Total Quantity": 86, "cost": 2500, "id": 30124, "Price/Cost": 14.3072}, {"Name": "Craftsman's Cunning Materia X", "Average Price": 3266, "Total Market": 1077812, "Total Quantity": 330, "cost": 1500, "id": 33939, "Price/Cost": 2.1773333333333333}, {"Name": "Craftsman's Command Materia IX", "Average Price": 7511, "Total Market": 54592156, "Total Quantity": 7268, "cost": 750, "id": 33927, "Price/Cost": 10.014666666666667}, {"Name": "Craftsman's Command Materia X", "Average Price": 18118, "Total Market": 39190341, "Total Quantity": 2163, "cost": 1500, "id": 33940, "Price/Cost": 12.078666666666667}, {"Name": "Gatherer's Guerdon Materia IX", "Average Price": 13626, "Total Market": 37253901, "Total Quantity": 2734, "cost": 750, "id": 33922, "Price/Cost": 18.168}, {"Name": "Gatherer's Guerdon Materia X", "Average Price": 10401, "Total Market": 14260666, "Total Quantity": 1371, "cost": 1500, "id": 33935, "Price/Cost": 6.934}, {"Name": "Gatherer's Guile Materia IX", "Average Price": 12838, "Total Market": 39708316, "Total Quantity": 3093, "cost": 750, "id": 33923, "Price/Cost": 17.117333333333335}, {"Name": "Gatherer's Guile Materia X", "Average Price": 8696, "Total Market": 9218483, "Total Quantity": 1060, "cost": 1500, "id": 33936, "Price/Cost": 5.7973333333333334}, {"Name": "Gatherer's Grasp Materia IX", "Average Price": 8427, "Total Market": 13896315, "Total Quantity": 1649, "cost": 750, "id": 33924, "Price/Cost": 11.236}, {"Name": "Gatherer's Grasp Materia X", "Average Price": 1940, "Total Market": 1391261, "Total Quantity": 717, "cost": 1500, "id": 33937, "Price/Cost": 1.2933333333333332}, {"Name": "Craftsman's Competence Materia IX", "Average Price": 3396, "Total Market": 5043203, "Total Quantity": 1485, "cost": 750, "id": 33925, "Price/Cost": 4.528}, {"Name": "Craftsman's Competence Materia X", "Average Price": 9231, "Total Market": 9776513, "Total Quantity": 1059, "cost": 1500, "id": 33938, "Price/Cost": 6.154}, {"Name": "Craftsman's Cunning Materia IX", "Average Price": 9186, "Total Market": 10297878, "Total Quantity": 1121, "cost": 750, "id": 33926, "Price/Cost": 12.248}]}