{"columns": ["Name", "Average Price", "Total Market", "Total Quantity", "cost", "id", "lodestone_id", "Price/Cost"], "items": [{"Name": "Crystarium Striking Dummy", "Average Price": 0, "Total Market": 0, "Total Quantity": 0, "cost": 300, "id": 27315, "lodestone_id": "87951d7d39d", "Price/Cost": 0.0}, {"Name": "Rencounter Orchestrion Roll", "Average Price": 0, "Total Market": 0, "Total Quantity": 0, "cost": 300, "id": 27917, "lodestone_id": "c6acc169198", "Price/Cost": 0.0}, {"Name": "Piety Materia VII", "Average Price": 127, "Total Market": 1143, "Total Quantity": 9, "cost": 150, "id": 25186, "lodestone_id": "c2be6ee80a9", "Price/Cost": 0.8466666666666667}, {"Name": "Heavens' Eye Materia VII", "Average Price": 135, "Total Market": 815, "Total Quantity": 6, "cost": 150, "id": 25187, "lodestone_id": "85587a58d9a", "Price/Cost": 0.9}, {"Name": "Savage Aim Materia VII", "Average Price": 138, "Total Market": 1108, "Total Quantity": 8, "cost": 150, "id": 25188, "lodestone_id": "ae193b74ae4", "Price/Cost": 0.92}, {"Name": "Savage Might Materia VII", "Average Price": 139, "Total Market": 3347, "Total Quantity": 24, "cost": 150, "id": 25189, "lodestone_id": "a3870117f91", "Price/Cost": 0.9266666666666666}, {"Name": "Battledance Materia VII", "Average Price": 143, "Total Market": 6447, "Total Quantity": 45, "cost": 150, "id": 25190, "lodestone_id": "d45e4b5e3ef", "Price/Cost": 0.9533333333333334}, {"Name": "Quickarm Materia VII", "Average Price": 155, "Total Market": 155, "Total Quantity": 1, "cost": 150, "id": 25197, "lodestone_id": "adeb9e0a07c", "Price/Cost": 1.0333333333333334}, {"Name": "Quicktongue Materia VII", "Average Price": 146, "Total Market": 1467, "Total Quantity": 10, "cost": 150, "id": 25198, "lodestone_id": "117f1387915", "Price/Cost": 0.9733333333333334}, {"Name": "Piety Materia VIII", "Average Price": 0, "Total Market": 0, "Total Quantity": 0, "cost": 400, "id": 26727, "lodestone_id": "58c35d174da", "Price/Cost": 0.0}, {"Name": "Heavens' Eye Materia VIII", "Average Price": 538, "Total Market": 17770, "Total Quantity": 33, "cost": 400, "id": 26728, "lodestone_id": "790e514496c", "Price/Cost": 1.345}, {"Name": "Savage Aim Materia VIII", "Average Price": 233, "Total Market": 14975, "Total Quantity": 64, "cost": 400, "id": 26729, "lodestone_id": "cd92a6cfb05", "Price/Cost": 0.5825}, {"Name": "Savage Might Materia VIII", "Average Price": 194, "Total Market": 22813, "Total Quantity": 117, "cost": 400, "id": 26730, "lodestone_id": "dcb31ada91b", "Price/Cost": 0.485}, {"Name": "Battledance Materia VIII", "Average Price": 0, "Total Market": 0, "Total Quantity": 0, "cost": 400, "id": 26731, "lodestone_id": "7def76b6ceb", "Price/Cost": 0.0}, {"Name": "Quickarm Materia VIII", "Average Price": 150, "Total Market": 150, "Total Quantity": 1, "cost": 400, "id": 26738, "lodestone_id": "70a73ce8da9", "Price/Cost": 0.375}, {"Name": "Quicktongue Materia VIII", "Average Price": 1343, "Total Market": 32239, "Total Quantity": 24, "cost": 400, "id": 26739, "lodestone_id": "a2a3c61d70b", "Price/Cost": 3.3575}, {"Name": "Thavnairian Striking Dummy", "Average Price": 0, "Total Market": 0, "Total Quantity": 0, "cost": 300, "id": 35804, "lodestone_id": "540db532f75", "Price/Cost": 0.0}, {"Name": "Unbowed Orchestrion Roll", "Average Price": 0, "Total Market": 0, "Total Quantity": 0, "cost": 300, "id": 36367, "lodestone_id": "c1847e3e3e3", "Price/Cost": 0.0}, {"Name": "Piety Materia IX", "Average Price": 110, "Total Market": 20188, "Total Quantity": 183, "cost": 150, "id": 33917, "lodestone_id": "b5e80dc8ce6", "Price/Cost": 0.7333333333333333}, {"Name": "Heavens' Eye Materia IX", "Average Price": 614, "Total Market": 66350, "Total Quantity": 108, "cost": 150, "id": 33918, "lodestone_id": "6c33b180bfb", "Price/Cost": 4.093333333333334}, {"Name": "Savage Aim Materia IX", "Average Price": 210, "Total Market": 64196, "Total Quantity": 305, "cost": 150, "id": 33919, "lodestone_id": "fb86de99514", "Price/Cost": 1.4}, {"Name": "Savage Might Materia IX", "Average Price": 154, "Total Market": 9764, "Total Quantity": 63, "cost": 150, "id": 33920, "lodestone_id": "86ae2ca0af4", "Price/Cost": 1.0266666666666666}, {"Name": "Battledance Materia IX", "Average Price": 102, "Total Market": 18417, "Total Quantity": 179, "cost": 150, "id": 33921, "lodestone_id": "dfec39007e3", "Price/Cost": 0.68}, {"Name": "Quickarm Materia IX", "Average Price": 92, "Total Market": 7117, "Total Quantity": 77, "cost": 150, "id": 33928, "lodestone_id": "89b34b48665", "Price/Cost": 0.6133333333333333}, {"Name": "Quicktongue Materia IX", "Average Price": 68, "Total Market": 4843, "Total Quantity": 71, "cost": 150, "id": 33929, "lodestone_id": "7b373e9fe7c", "Price/Cost": 0.4533333333333333}, {"Name": "Piety Materia X", "Average Price": 283, "Total Market": 567, "Total Quantity": 2, "cost": 400, "id": 33930, "lodestone_id": "de867f3ebcd", "Price/Cost": 0.7075}, {"Name": "Heavens' Eye Materia X", "Average Price": 441, "Total Market": 124868, "Total Quantity": 283, "cost": 400, "id": 33931, "lodestone_id": "41be9b69cd7", "Price/Cost": 1.1025}, {"Name": "Savage Aim Materia X", "Average Price": 443, "Total Market": 206072, "Total Quantity": 465, "cost": 400, "id": 33932, "lodestone_id": "e211a9e9532", "Price/Cost": 1.1075}, {"Name": "Savage Might Materia X", "Average Price": 382, "Total Market": 34455, "Total Quantity": 90, "cost": 400, "id": 33933, "lodestone_id": "2a6b57d608b", "Price/Cost": 0.955}, {"Name": "Battledance Materia X", "Average Price": 216, "Total Market": 5846, "Total Quantity": 27, "cost": 400, "id": 33934, "lodestone_id": "7e1f37947ee", "Price/Cost": 0.54}, {"Name": "Quickarm Materia X", "Average Price": 150, "Total Market": 1200, "Total Quantity": 8, "cost": 400, "id": 33941, "lodestone_id": "3733c5e95db", "Price/Cost": 0.375}, {"Name": "Quicktongue Materia X", "Average Price": 153, "Total Market": 2450, "Total Quantity": 16, "cost": 400, "id": 33942, "lodestone_id": "d777fd76997", "Price/Cost": 0.3825}, {"Name": "Piety Materia XI", "Average Price": 585, "Total Market": 166837, "Total Quantity": 285, "cost": 150, "id": 41757, "lodestone_id": "e5f85aeb2fb", "Price/Cost": 3.9}, {"Name": "Heavens' Eye Materia XI", "Average Price": 6140, "Total Market": 6994542, "Total Quantity": 1139, "cost": 150, "id": 41758, "lodestone_id": "cf1ab631062", "Price/Cost": 40.93333333333333}, {"Name": "Savage Aim Materia XI", "Average Price": 4943, "Total Market": 6367037, "Total Quantity": 1288, "cost": 150, "id": 41759, "lodestone_id": "7522d2aff11", "Price/Cost": 32.95333333333333}, {"Name": "Savage Might Materia XI", "Average Price": 5310, "Total Market": 3834435, "Total Quantity": 722, "cost": 150, "id": 41760, "lodestone_id": "cfc13243f27", "Price/Cost": 35.4}, {"Name": "Battledance Materia XI", "Average Price": 967, "Total Market": 185689, "Total Quantity": 192, "cost": 150, "id": 41761, "lodestone_id": "15ba67565a3", "Price/Cost": 6.446666666666666}, {"Name": "Quickarm Materia XI", "Average Price": 1309, "Total Market": 230425, "Total Quantity": 176, "cost": 150, "id": 41768, "lodestone_id": "97ac13e0c0a", "Price/Cost": 8.726666666666667}, {"Name": "Quicktongue Materia XI", "Average Price": 734, "Total Market": 287944, "Total Quantity": 392, "cost": 150, "id": 41769, "lodestone_id": "4c0e76e8580", "Price/Cost": 4.8933333333333335}, {"Name": "Piety Materia XII", "Average Price": 1289, "Total Market": 92817, "Total Quantity": 72, "cost": 400, "id": 41770, "lodestone_id": "5041e5bcd77", "Price/Cost": 3.2225}, {"Name": "Heavens' Eye Materia XII", "Average Price": 15194, "Total Market": 11030892, "Total Quantity": 726, "cost": 400, "id": 41771, "lodestone_id": "becc400e5a0", "Price/Cost": 37.985}, {"Name": "Savage Aim Materia XII", "Average Price": 14430, "Total Market": 11717476, "Total Quantity": 812, "cost": 400, "id": 41772, "lodestone_id": "c5e1332aa1b", "Price/Cost": 36.075}, {"Name": "Savage Might Materia XII", "Average Price": 15878, "Total Market": 7621753, "Total Quantity": 480, "cost": 400, "id": 41773, "lodestone_id": "c8202fc3f4e", "Price/Cost": 39.695}, {"Name": "Battledance Materia XII", "Average Price": 1365, "Total Market": 79221, "Total Quantity": 58, "cost": 400, "id": 41774, "lodestone_id": "b503c2ec8ef", "Price/Cost": 3.4125}, {"Name": "Quickarm Materia XII", "Average Price": 8648, "Total Market": 934026, "Total Quantity": 108, "cost": 400, "id": 41781, "lodestone_id": "e9de0dfd354", "Price/Cost": 21.62}, {"Name": "Quicktongue Materia XII", "Average Price": 5742, "Total Market": 545552, "Total Quantity": 95, "cost": 400, "id": 41782, "lodestone_id": "6e82e0295b6", "Price/Cost": 14.355}]}