{"columns": ["Name", "Average Price", "Total Market", "Total Quantity", "cost", "id", "Price/Cost"], "items": [{"Name": "Ruby Red Dye", "Average Price": 8495, "Total Market": 331318, "Total Quantity": 39, "cost": 500, "id": 30116, "Price/Cost": 16.99}, {"Name": "Cherry Pink Dye", "Average Price": 9965, "Total Market": 179373, "Total Quantity": 18, "cost": 500, "id": 30117, "Price/Cost": 19.93}, {"Name": "Canary Yellow Dye", "Average Price": 0, "Total Market": 0, "Total Quantity": 0, "cost": 500, "id": 30118, "Price/Cost": 0.0}, {"Name": "Vanilla Yellow Dye", "Average Price": 4398, "Total Market": 21990, "Total Quantity": 5, "cost": 500, "id": 30119, "Price/Cost": 8.796}, {"Name": "Dragoon Blue Dye", "Average Price": 9223, "Total Market": 867053, "Total Quantity": 94, "cost": 500, "id": 30120, "Price/Cost": 18.446}, {"Name": "Turquoise Blue Dye", "Average Price": 9994, "Total Market": 199896, "Total Quantity": 20, "cost": 500, "id": 30121, "Price/Cost": 19.988}, {"Name": "Gunmetal Black Dye", "Average Price": 17853, "Total Market": 642741, "Total Quantity": 36, "cost": 2500, "id": 30122, "Price/Cost": 7.1412}, {"Name": "Pearl White Dye", "Average Price": 18882, "Total Market": 849729, "Total Quantity": 45, "cost": 2500, "id": 30123, "Price/Cost": 7.5528}, {"Name": "Metallic Brass Dye", "Average Price": 31796, "Total Market": 31796, "Total Quantity": 1, "cost": 2500, "id": 30124, "Price/Cost": 12.7184}, {"Name": "Craftsman's Cunning Materia X", "Average Price": 410, "Total Market": 62783, "Total Quantity": 153, "cost": 1500, "id": 33939, "Price/Cost": 0.2733333333333333}, {"Name": "Craftsman's Command Materia IX", "Average Price": 5117, "Total Market": 583437, "Total Quantity": 114, "cost": 750, "id": 33927, "Price/Cost": 6.822666666666667}, {"Name": "Craftsman's Command Materia X", "Average Price": 4569, "Total Market": 552870, "Total Quantity": 121, "cost": 1500, "id": 33940, "Price/Cost": 3.046}, {"Name": "Gatherer's Guerdon Materia IX", "Average Price": 6489, "Total Market": 233604, "Total Quantity": 36, "cost": 750, "id": 33922, "Price/Cost": 8.652}, {"Name": "Gatherer's Guerdon Materia X", "Average Price": 7975, "Total Market": 374862, "Total Quantity": 47, "cost": 1500, "id": 33935, "Price/Cost": 5.316666666666666}, {"Name": "Gatherer's Guile Materia IX", "Average Price": 7491, "Total Market": 269710, "Total Quantity": 36, "cost": 750, "id": 33923, "Price/Cost": 9.988}, {"Name": "Gatherer's Guile Materia X", "Average Price": 4564, "Total Market": 292147, "Total Quantity": 64, "cost": 1500, "id": 33936, "Price/Cost": 3.042666666666667}, {"Name": "Gatherer's Grasp Materia IX", "Average Price": 7898, "Total Market": 315920, "Total Quantity": 40, "cost": 750, "id": 33924, "Price/Cost": 10.530666666666667}, {"Name": "Gatherer's Grasp Materia X", "Average Price": 739, "Total Market": 3696, "Total Quantity": 5, "cost": 1500, "id": 33937, "Price/Cost": 0.49266666666666664}, {"Name": "Craftsman's Competence Materia IX", "Average Price": 1664, "Total Market": 412817, "Total Quantity": 248, "cost": 750, "id": 33925, "Price/Cost": 2.2186666666666666}, {"Name": "Craftsman's Competence Materia X", "Average Price": 1196, "Total Market": 114883, "Total Quantity": 96, "cost": 1500, "id": 33938, "Price/Cost": 0.7973333333333333}, {"Name": "Craftsman's Cunning Materia IX", "Average Price": 2448, "Total Market": 276648, "Total Quantity": 113, "cost": 750, "id": 33926, "Price/Cost": 3.264}]}