{"columns": ["Name", "Average Price", "Total Market", "Total Quantity", "cost", "id", "Price/Cost"], "items": [{"Name": "Craftsman's Competence Materia X", "Average Price": 5929, "Total Market": 15138530, "Total Quantity": 2553, "cost": 500, "id": 33938, "Price/Cost": 11.858}, {"Name": "Craftsman's Cunning Materia X", "Average Price": 1684, "Total Market": 2713552, "Total Quantity": 1611, "cost": 500, "id": 33939, "Price/Cost": 3.368}, {"Name": "Craftsman's Command Materia X", "Average Price": 19931, "Total Market": 83494015, "Total Quantity": 4189, "cost": 500, "id": 33940, "Price/Cost": 39.862}, {"Name": "Immutable Solution", "Average Price": 6444, "Total Market": 50349520, "Total Quantity": 7813, "cost": 125, "id": 37284, "Price/Cost": 51.552}, {"Name": "Prime Loaghtan Rump", "Average Price": 0, "Total Market": 0, "Total Quantity": 0, "cost": 15, "id": 38273, "Price/Cost": 0.0}, {"Name": "Sunset Carrot", "Average Price": 65, "Total Market": 15880, "Total Quantity": 243, "cost": 15, "id": 38272, "Price/Cost": 4.333333333333333}, {"Name": "Piennolo Tomato", "Average Price": 7, "Total Market": 350, "Total Quantity": 50, "cost": 15, "id": 38274, "Price/Cost": 0.4666666666666667}, {"Name": "Thundermelon", "Average Price": 0, "Total Market": 0, "Total Quantity": 0, "cost": 15, "id": 38271, "Price/Cost": 0.0}, {"Name": "King Urchin", "Average Price": 0, "Total Market": 0, "Total Quantity": 0, "cost": 15, "id": 38275, "Price/Cost": 0.0}, {"Name": "Butterbeef", "Average Price": 46, "Total Market": 140, "Total Quantity": 3, "cost": 10, "id": 36099, "Price/Cost": 4.6}, {"Name": "Giant Pumpkin", "Average Price": 25, "Total Market": 1244, "Total Quantity": 48, "cost": 10, "id": 36100, "Price/Cost": 2.5}, {"Name": "White Peach", "Average Price": 0, "Total Market": 0, "Total Quantity": 0, "cost": 10, "id": 36101, "Price/Cost": 0.0}, {"Name": "Subtle Cinnamon Sticks", "Average Price": 97, "Total Market": 5244, "Total Quantity": 54, "cost": 10, "id": 36102, "Price/Cost": 9.7}, {"Name": "Glass Scallop", "Average Price": 0, "Total Market": 0, "Total Quantity": 0, "cost": 10, "id": 36103, "Price/Cost": 0.0}]}